MANIFEST.in
README.md
setup.py
hashutils/__init__.py
hashutils/hashutils.py
hashutils.egg-info/PKG-INFO
hashutils.egg-info/SOURCES.txt
hashutils.egg-info/dependency_links.txt
hashutils.egg-info/not-zip-safe
hashutils.egg-info/top_level.txt