Metadata-Version: 1.1
Name: hashutils
Version: 0.0.3
Summary: Utility functions for hashing arrays, combining hashes.
Home-page: https://github.com/timothydmorton/hashutils
Author: Timothy D. Morton
Author-email: tim.morton@gmail.com
License: UNKNOWN
Platform: UNKNOWN
Classifier: Development Status :: 3 - Alpha
Classifier: Intended Audience :: Science/Research
Classifier: License :: OSI Approved :: GNU General Public License (GPL)
Classifier: Operating System :: OS Independent
Classifier: Programming Language :: Python
